openai_parallel_toolkit/__init__.py
openai_parallel_toolkit/main.py
openai_parallel_toolkit/api/__init__.py
openai_parallel_toolkit/api/keys.py
openai_parallel_toolkit/api/model.py
openai_parallel_toolkit/api/request.py
openai_parallel_toolkit/utils/__init__.py
openai_parallel_toolkit/utils/logger.py
openai_parallel_toolkit/utils/process_bar.py
openai_parallel_toolkit/utils/reader.py
openai_parallel_toolkit-1.1.3.dist-info/LICENSE
openai_parallel_toolkit-1.1.3.dist-info/METADATA
openai_parallel_toolkit-1.1.3.dist-info/WHEEL
openai_parallel_toolkit-1.1.3.dist-info/top_level.txt
openai_parallel_toolkit-1.1.3.dist-info/RECORD
