Metadata-Version: 2.1
Name: openai-parallel-toolkit
Version: 1.1.3
Summary: OpenAI-Parallel-Toolkit is a Python library for handling multiple OpenAI API keys and parallel tasks. It provides API key rotation, multithreading for faster task execution, and utility functions to boost your OpenAI integration. Ideal for efficient large-scale OpenAI usage.
Home-page: https://github.com/CZT0/OpenAI-Parallel-Toolkit
Author: Jellow
Author-email: dvdx@foxmail.com
Classifier: Development Status :: 3 - Alpha
Classifier: License :: OSI Approved :: MIT License
Classifier: Programming Language :: Python :: 3.8
Classifier: Programming Language :: Python :: 3.9
Classifier: Programming Language :: Python :: 3.10
Classifier: Programming Language :: Python :: 3.11
Requires-Python: >=3.8
License-File: LICENSE
Requires-Dist: openai
Requires-Dist: colorlog
Requires-Dist: tqdm
Requires-Dist: cachetools
